markji_wordcard_assistant/__init__.py
markji_wordcard_assistant/__main__.py
markji_wordcard_assistant/trans.py
markji_wordcard_assistant/units.py
markji_wordcard_assistant/fast_api/__init__.py
markji_wordcard_assistant/fast_api/exception.py
markji_wordcard_assistant/fast_api/jobs.py
markji_wordcard_assistant/fast_api/main.py
markji_wordcard_assistant/fast_api/service.py
markji_wordcard_assistant/fast_api/controller/__init__.py
markji_wordcard_assistant/fast_api/controller/jobs_controller.py
markji_wordcard_assistant/fast_api/controller/result.py
markji_wordcard_assistant/fast_api/controller/trans_file.py
markji_wordcard_assistant/fast_api/controller/trans_text.py
markji_wordcard_assistant/markji_api/__init__.py
markji_wordcard_assistant/markji_api/api.py
markji_wordcard_assistant/open_api/__init__.py
markji_wordcard_assistant/open_api/exception.py
markji_wordcard_assistant/open_api/jobs.py
markji_wordcard_assistant/open_api/main.py
markji_wordcard_assistant/open_api/service.py
markji_wordcard_assistant/open_api/controller/__init__.py
markji_wordcard_assistant/open_api/controller/jobs_controller.py
markji_wordcard_assistant/open_api/controller/result.py
markji_wordcard_assistant/open_api/controller/trans_controller.py
markji_wordcard_assistant/voice/__init__.py
markji_wordcard_assistant/voice/edge.py
markji_wordcard_assistant/voice/elevenlab.py
markji_wordcard_assistant/voice/markji_native.py
markji_wordcard_assistant/voice/openai_tts.py
markji_wordcard_assistant/voice/sepcific.md
markji_wordcard_assistant/voice/tts_method.py
markji_wordcard_assistant/voice/youdao.py
markji_wordcard_assistant-0.4.0.dist-info/LICENSE
markji_wordcard_assistant-0.4.0.dist-info/METADATA
markji_wordcard_assistant-0.4.0.dist-info/WHEEL
markji_wordcard_assistant-0.4.0.dist-info/top_level.txt
markji_wordcard_assistant-0.4.0.dist-info/RECORD
