Metadata-Version: 2.1
Name: markji-wordcard-assistant
Version: 0.4.0
Summary: 制作markji英文听写卡片的工具
Author: LiYiMing
License: MIT License
Requires-Python: >=3.10
License-File: LICENSE
Requires-Dist: pip
Requires-Dist: requests
Requires-Dist: httpx
Requires-Dist: httpx[socks]
Requires-Dist: pyperclip
Requires-Dist: edge-tts
Requires-Dist: openai >=1.2.0
Requires-Dist: elevenlabs
Requires-Dist: fastapi
Requires-Dist: uvicorn[standard]
Requires-Dist: python-multipart
Requires-Dist: email-validator
